{
  "boxrec_id": "936958",
  "boxrec_url": "https://boxrec.com/en/box-pro/936958",
  "boxrec_wiki_url": "https://boxrec.com/wiki/index.php?title=Human:936958",
  "slug": "floyd-schofield",
  "full_name": "Floyd Schofield",
  "birth_name": "Floyd III Schofield",
  "nickname": null,
  "image_url": null,
  "date_of_birth": null,
  "weight": null,
  "bio": null,
  "trainer": null,
  "gym": null,
  "residence": "Austin, Texas, USA",
  "birth_place": "Jersey City, New Jersey, USA",
  "gender": "male",
  "nationality": "USA",
  "height": "5\u2032 7\u2033 / 170cm",
  "reach": null,
  "stance": "orthodox",
  "promoter": null,
  "manager": "Michael Miller",
  "pro_debut_date": "2020-10-09",
  "pro_division": "light",
  "pro_wins": 19,
  "pro_wins_by_knockout": 0,
  "pro_losses": 0,
  "pro_losses_by_knockout": null,
  "pro_draws": 0,
  "pro_status": null,
  "pro_total_bouts": 19,
  "pro_total_rounds": 78,
  "amateur_debut_date": null,
  "amateur_division": null,
  "amateur_wins": null,
  "amateur_wins_by_knockout": null,
  "amateur_losses": null,
  "amateur_losses_by_knockout": null,
  "amateur_draws": null,
  "amateur_status": null,
  "amateur_total_bouts": null,
  "amateur_total_rounds": null,
  "rating": "",
  "ranking": null,
  "titles": [],
  "ko_percentage": "68.42%",
  "created_at": "2025-07-31T04:21:21.947351+00:00",
  "updated_at": "2025-07-31T04:21:21.947352+00:00",
  "bouts": [
    {
      "bout_date": "2025-06-28",
      "opponent_name": "Tevin Farmer",
      "opponent_id": "562946",
      "opponent_url": "https://boxrec.com/en/box-pro/562946",
      "opponent_weight": null,
      "opponent_record": "33-8-1",
      "recent_form": "WWWLLL",
      "venue_name": "Honda Center, Anaheim",
      "referee_name": null,
      "judge_1_name": null,
      "judge_1_score": null,
      "judge_2_name": null,
      "judge_2_score": null,
      "judge_3_name": null,
      "judge_3_score": null,
      "num_rounds_scheduled": null,
      "result": "W",
      "result_method": null,
      "result_round": null,
      "event_page_link": null,
      "bout_page_link": null,
      "scorecards_page_link": null,
      "title_fight": null,
      "bout_rating": 3
    },
    {
      "bout_date": "Nov 24",
      "opponent_name": "Rene Tellez Giron",
      "opponent_id": "771680",
      "opponent_url": "https://boxrec.com/en/box-pro/771680",
      "opponent_weight": null,
      "opponent_record": "20-3-0",
      "recent_form": "LWLWWW",
      "venue_name": "Virgin Hotels Las Vegas, Las Vegas",
      "referee_name": null,
      "judge_1_name": null,
      "judge_1_score": null,
      "judge_2_name": null,
      "judge_2_score": null,
      "judge_3_name": null,
      "judge_3_score": null,
      "num_rounds_scheduled": null,
      "result": "W",
      "result_method": null,
      "result_round": null,
      "event_page_link": null,
      "bout_page_link": null,
      "scorecards_page_link": null,
      "title_fight": null,
      "bout_rating": 3
    },
    {
      "bout_date": "Mar 24",
      "opponent_name": "Esteuri Suero",
      "opponent_id": "874107",
      "opponent_url": "https://boxrec.com/en/box-pro/874107",
      "opponent_weight": null,
      "opponent_record": "13-1-0",
      "recent_form": "WWWWLW",
      "venue_name": "The Cosmopolitan of Las Vegas, Chelsea Ballroom, Las Vegas",
      "referee_name": null,
      "judge_1_name": null,
      "judge_1_score": null,
      "judge_2_name": null,
      "judge_2_score": null,
      "judge_3_name": null,
      "judge_3_score": null,
      "num_rounds_scheduled": null,
      "result": "W",
      "result_method": null,
      "result_round": null,
      "event_page_link": null,
      "bout_page_link": null,
      "scorecards_page_link": null,
      "title_fight": null,
      "bout_rating": 2
    },
    {
      "bout_date": "Dec 23",
      "opponent_name": "Ricardo Lopez Torres",
      "opponent_id": "752477",
      "opponent_url": "https://boxrec.com/en/box-pro/752477",
      "opponent_weight": null,
      "opponent_record": "17-7-3",
      "recent_form": "WWLLW",
      "venue_name": "Toyota Center, Houston",
      "referee_name": null,
      "judge_1_name": null,
      "judge_1_score": null,
      "judge_2_name": null,
      "judge_2_score": null,
      "judge_3_name": null,
      "judge_3_score": null,
      "num_rounds_scheduled": null,
      "result": "W",
      "result_method": null,
      "result_round": null,
      "event_page_link": null,
      "bout_page_link": null,
      "scorecards_page_link": null,
      "title_fight": null,
      "bout_rating": 1
    },
    {
      "bout_date": "Jul 23",
      "opponent_name": "Haskell Rhodes",
      "opponent_id": "567354",
      "opponent_url": "https://boxrec.com/en/box-pro/567354",
      "opponent_weight": null,
      "opponent_record": "28-4-1",
      "recent_form": "WWLWLW",
      "venue_name": "AT&T Center, San Antonio",
      "referee_name": null,
      "judge_1_name": null,
      "judge_1_score": null,
      "judge_2_name": null,
      "judge_2_score": null,
      "judge_3_name": null,
      "judge_3_score": null,
      "num_rounds_scheduled": null,
      "result": "W",
      "result_method": null,
      "result_round": null,
      "event_page_link": null,
      "bout_page_link": null,
      "scorecards_page_link": null,
      "title_fight": null,
      "bout_rating": 1
    },
    {
      "bout_date": "Apr 23",
      "opponent_name": "Jesus Valentin Leon",
      "opponent_id": "769527",
      "opponent_url": "https://boxrec.com/en/box-pro/769527",
      "opponent_weight": null,
      "opponent_record": "23-1-2",
      "recent_form": "WWWWWW",
      "venue_name": "T-Mobile Arena, Las Vegas",
      "referee_name": null,
      "judge_1_name": null,
      "judge_1_score": null,
      "judge_2_name": null,
      "judge_2_score": null,
      "judge_3_name": null,
      "judge_3_score": null,
      "num_rounds_scheduled": null,
      "result": "W",
      "result_method": null,
      "result_round": null,
      "event_page_link": null,
      "bout_page_link": null,
      "scorecards_page_link": null,
      "title_fight": null,
      "bout_rating": 1
    },
    {
      "bout_date": "Jan 23",
      "opponent_name": "Alberto Mercado",
      "opponent_id": "503482",
      "opponent_url": "https://boxrec.com/en/box-pro/503482",
      "opponent_weight": null,
      "opponent_record": "17-4-1",
      "recent_form": "WLWLLW",
      "venue_name": "YouTube Theater, Inglewood",
      "referee_name": null,
      "judge_1_name": null,
      "judge_1_score": null,
      "judge_2_name": null,
      "judge_2_score": null,
      "judge_3_name": null,
      "judge_3_score": null,
      "num_rounds_scheduled": null,
      "result": "W",
      "result_method": null,
      "result_round": null,
      "event_page_link": null,
      "bout_page_link": null,
      "scorecards_page_link": null,
      "title_fight": null,
      "bout_rating": 1
    },
    {
      "bout_date": "Oct 22",
      "opponent_name": "Daniel Rosas",
      "opponent_id": "430922",
      "opponent_url": "https://boxrec.com/en/box-pro/430922",
      "opponent_weight": null,
      "opponent_record": "22-5-1",
      "recent_form": "WLLWWL",
      "venue_name": "Fantasy Springs Casino, Indio",
      "referee_name": null,
      "judge_1_name": null,
      "judge_1_score": null,
      "judge_2_name": null,
      "judge_2_score": null,
      "judge_3_name": null,
      "judge_3_score": null,
      "num_rounds_scheduled": null,
      "result": "W",
      "result_method": null,
      "result_round": null,
      "event_page_link": null,
      "bout_page_link": null,
      "scorecards_page_link": null,
      "title_fight": null,
      "bout_rating": 1
    },
    {
      "bout_date": "Aug 22",
      "opponent_name": "Rodrigo Guerrero",
      "opponent_id": "330468",
      "opponent_url": "https://boxrec.com/en/box-pro/330468",
      "opponent_weight": null,
      "opponent_record": "26-14-2",
      "recent_form": "LLLLLL",
      "venue_name": "Dickies Arena, Fort Worth",
      "referee_name": null,
      "judge_1_name": null,
      "judge_1_score": null,
      "judge_2_name": null,
      "judge_2_score": null,
      "judge_3_name": null,
      "judge_3_score": null,
      "num_rounds_scheduled": null,
      "result": "W",
      "result_method": null,
      "result_round": null,
      "event_page_link": null,
      "bout_page_link": null,
      "scorecards_page_link": null,
      "title_fight": null,
      "bout_rating": 1
    },
    {
      "bout_date": "May 22",
      "opponent_name": "Juan Antonio Lopez",
      "opponent_id": "634959",
      "opponent_url": "https://boxrec.com/en/box-pro/634959",
      "opponent_weight": null,
      "opponent_record": "17-9-0",
      "recent_form": "LWLLWW",
      "venue_name": "Davies Boxing and Fitness, San Antonio",
      "referee_name": null,
      "judge_1_name": null,
      "judge_1_score": null,
      "judge_2_name": null,
      "judge_2_score": null,
      "judge_3_name": null,
      "judge_3_score": null,
      "num_rounds_scheduled": null,
      "result": "W",
      "result_method": null,
      "result_round": null,
      "event_page_link": null,
      "bout_page_link": null,
      "scorecards_page_link": null,
      "title_fight": null,
      "bout_rating": 1
    },
    {
      "bout_date": "Feb 22",
      "opponent_name": "Julio Sanchez",
      "opponent_id": "701573",
      "opponent_url": "https://boxrec.com/en/box-pro/701573",
      "opponent_weight": null,
      "opponent_record": "5-5-1",
      "recent_form": "LWLWWD",
      "venue_name": "Davies Boxing and Fitness, San Antonio",
      "referee_name": null,
      "judge_1_name": null,
      "judge_1_score": null,
      "judge_2_name": null,
      "judge_2_score": null,
      "judge_3_name": null,
      "judge_3_score": null,
      "num_rounds_scheduled": null,
      "result": "W",
      "result_method": null,
      "result_round": null,
      "event_page_link": null,
      "bout_page_link": null,
      "scorecards_page_link": null,
      "title_fight": null,
      "bout_rating": 0
    },
    {
      "bout_date": "Oct 21",
      "opponent_name": "Pedro Vicente Scharbaai",
      "opponent_id": "614853",
      "opponent_url": "https://boxrec.com/en/box-pro/614853",
      "opponent_weight": null,
      "opponent_record": "7-3-1",
      "recent_form": "WLWWDL",
      "venue_name": "Davies Boxing and Fitness, San Antonio",
      "referee_name": null,
      "judge_1_name": null,
      "judge_1_score": null,
      "judge_2_name": null,
      "judge_2_score": null,
      "judge_3_name": null,
      "judge_3_score": null,
      "num_rounds_scheduled": null,
      "result": "W",
      "result_method": null,
      "result_round": null,
      "event_page_link": null,
      "bout_page_link": null,
      "scorecards_page_link": null,
      "title_fight": null,
      "bout_rating": 1
    },
    {
      "bout_date": "Aug 21",
      "opponent_name": "Roberto Almazan Monreal",
      "opponent_id": "708380",
      "opponent_url": "https://boxrec.com/en/box-pro/708380",
      "opponent_weight": null,
      "opponent_record": "10-14-0",
      "recent_form": "WLLLLW",
      "venue_name": "Davies Boxing and Fitness, San Antonio",
      "referee_name": null,
      "judge_1_name": null,
      "judge_1_score": null,
      "judge_2_name": null,
      "judge_2_score": null,
      "judge_3_name": null,
      "judge_3_score": null,
      "num_rounds_scheduled": null,
      "result": "W",
      "result_method": null,
      "result_round": null,
      "event_page_link": null,
      "bout_page_link": null,
      "scorecards_page_link": null,
      "title_fight": null,
      "bout_rating": 0
    },
    {
      "bout_date": "Jun 21",
      "opponent_name": "Darryl Hayes",
      "opponent_id": "484868",
      "opponent_url": "https://boxrec.com/en/box-pro/484868",
      "opponent_weight": null,
      "opponent_record": "7-15-0",
      "recent_form": "WLLLWL",
      "venue_name": "Buckhead Fight Club, Atlanta",
      "referee_name": null,
      "judge_1_name": null,
      "judge_1_score": null,
      "judge_2_name": null,
      "judge_2_score": null,
      "judge_3_name": null,
      "judge_3_score": null,
      "num_rounds_scheduled": null,
      "result": "W",
      "result_method": null,
      "result_round": null,
      "event_page_link": null,
      "bout_page_link": null,
      "scorecards_page_link": null,
      "title_fight": null,
      "bout_rating": 0
    },
    {
      "bout_date": "May 21",
      "opponent_name": "Danny Flores",
      "opponent_id": "504958",
      "opponent_url": "https://boxrec.com/en/box-pro/504958",
      "opponent_weight": null,
      "opponent_record": "15-22-1",
      "recent_form": "LLLLLL",
      "venue_name": "Bryan Glazer Family JCC Auditorium, Tampa",
      "referee_name": null,
      "judge_1_name": null,
      "judge_1_score": null,
      "judge_2_name": null,
      "judge_2_score": null,
      "judge_3_name": null,
      "judge_3_score": null,
      "num_rounds_scheduled": null,
      "result": "W",
      "result_method": null,
      "result_round": null,
      "event_page_link": null,
      "bout_page_link": null,
      "scorecards_page_link": null,
      "title_fight": null,
      "bout_rating": 0
    },
    {
      "bout_date": "Apr 21",
      "opponent_name": "Mike Fowler",
      "opponent_id": "693302",
      "opponent_url": "https://boxrec.com/en/box-pro/693302",
      "opponent_weight": null,
      "opponent_record": "7-35-0",
      "recent_form": "LLLLLL",
      "venue_name": "Buckhead Fight Club, Atlanta",
      "referee_name": null,
      "judge_1_name": null,
      "judge_1_score": null,
      "judge_2_name": null,
      "judge_2_score": null,
      "judge_3_name": null,
      "judge_3_score": null,
      "num_rounds_scheduled": null,
      "result": "W",
      "result_method": null,
      "result_round": null,
      "event_page_link": null,
      "bout_page_link": null,
      "scorecards_page_link": null,
      "title_fight": null,
      "bout_rating": 0
    },
    {
      "bout_date": "Mar 21",
      "opponent_name": "Jonathan Conde",
      "opponent_id": "859260",
      "opponent_url": "https://boxrec.com/en/box-pro/859260",
      "opponent_weight": null,
      "opponent_record": "2-5-0",
      "recent_form": "LWLLWL",
      "venue_name": "Osceola Heritage Park, Kissimmee",
      "referee_name": null,
      "judge_1_name": null,
      "judge_1_score": null,
      "judge_2_name": null,
      "judge_2_score": null,
      "judge_3_name": null,
      "judge_3_score": null,
      "num_rounds_scheduled": null,
      "result": "W",
      "result_method": null,
      "result_round": null,
      "event_page_link": null,
      "bout_page_link": null,
      "scorecards_page_link": null,
      "title_fight": null,
      "bout_rating": 0
    },
    {
      "bout_date": "Jan 21",
      "opponent_name": "Cesar Valencia Aguilar",
      "opponent_id": "901257",
      "opponent_url": "https://boxrec.com/en/box-pro/901257",
      "opponent_weight": null,
      "opponent_record": "1-1-0",
      "recent_form": "LW",
      "venue_name": "Big Punch Arena, Tijuana",
      "referee_name": null,
      "judge_1_name": null,
      "judge_1_score": null,
      "judge_2_name": null,
      "judge_2_score": null,
      "judge_3_name": null,
      "judge_3_score": null,
      "num_rounds_scheduled": null,
      "result": "W",
      "result_method": null,
      "result_round": null,
      "event_page_link": null,
      "bout_page_link": null,
      "scorecards_page_link": null,
      "title_fight": null,
      "bout_rating": 0
    },
    {
      "bout_date": "Oct 20",
      "opponent_name": "Richard Esquibel",
      "opponent_id": "920313",
      "opponent_url": "https://boxrec.com/en/box-pro/920313",
      "opponent_weight": null,
      "opponent_record": null,
      "recent_form": null,
      "venue_name": "Osceola Heritage Park, Kissimmee",
      "referee_name": null,
      "judge_1_name": null,
      "judge_1_score": null,
      "judge_2_name": null,
      "judge_2_score": null,
      "judge_3_name": null,
      "judge_3_score": null,
      "num_rounds_scheduled": null,
      "result": "W",
      "result_method": null,
      "result_round": null,
      "event_page_link": null,
      "bout_page_link": null,
      "scorecards_page_link": null,
      "title_fight": null,
      "bout_rating": 0
    }
  ]
}