{
  "boxrec_id": "779719",
  "boxrec_url": "https://boxrec.com/en/box-pro/779719",
  "boxrec_wiki_url": "https://boxrec.com/wiki/index.php?title=Human:779719",
  "slug": "william-scull",
  "full_name": "William Scull",
  "birth_name": "William Scull Yero",
  "nickname": "El Indomable",
  "image_url": "https://boxrec.com/images/thumb/f/f9/779719_2025.jpg/200px-779719_2025.jpg",
  "residence": "Berlin, Germany",
  "birth_place": "Matanzas, Cuba",
  "date_of_birth": null,
  "gender": "male",
  "nationality": "Cuba",
  "height": "5\u2032 11\u00bd\u2033 / 182cm",
  "reach": null,
  "weight": null,
  "stance": "orthodox",
  "bio": null,
  "promoter": null,
  "trainer": null,
  "manager": null,
  "gym": null,
  "pro_debut_date": "2016-11-11",
  "pro_division": "super middle",
  "pro_wins": 23,
  "pro_wins_by_knockout": 0,
  "pro_losses": 1,
  "pro_losses_by_knockout": null,
  "pro_draws": 0,
  "pro_status": null,
  "pro_total_bouts": 24,
  "pro_total_rounds": 156,
  "amateur_debut_date": null,
  "amateur_division": null,
  "amateur_wins": null,
  "amateur_wins_by_knockout": null,
  "amateur_losses": null,
  "amateur_losses_by_knockout": null,
  "amateur_draws": null,
  "amateur_status": null,
  "amateur_total_bouts": null,
  "amateur_total_rounds": null,
  "rating": "",
  "ranking": null,
  "titles": [],
  "ko_percentage": "39.13%",
  "bouts": [
    {
      "bout_date": "May 25",
      "opponent_name": "Saul Alvarez",
      "opponent_id": "348759",
      "opponent_url": "https://boxrec.com/en/box-pro/348759",
      "opponent_weight": null,
      "opponent_record": "62-2-2",
      "recent_form": "LWWWWW",
      "venue_name": "The Venue Riyadh Season, Riyadh",
      "referee_name": null,
      "judge_1_name": null,
      "judge_1_score": null,
      "judge_2_name": null,
      "judge_2_score": null,
      "judge_3_name": null,
      "judge_3_score": null,
      "num_rounds_scheduled": null,
      "result": "loss",
      "result_method": null,
      "result_round": null,
      "event_page_link": "https://boxrec.com/en/event/915129",
      "bout_page_link": "https://boxrec.com/en/event/915129/3300177",
      "scorecards_page_link": null,
      "title_fight": null,
      "bout_rating": 4
    },
    {
      "bout_date": "Oct 24",
      "opponent_name": "Vladimir Shishkin",
      "opponent_id": "767596",
      "opponent_url": "https://boxrec.com/en/box-pro/767596",
      "opponent_weight": null,
      "opponent_record": "16-0-0",
      "recent_form": "WWWWWW",
      "venue_name": "Stadthalle, Falkensee",
      "referee_name": null,
      "judge_1_name": null,
      "judge_1_score": null,
      "judge_2_name": null,
      "judge_2_score": null,
      "judge_3_name": null,
      "judge_3_score": null,
      "num_rounds_scheduled": null,
      "result": "win",
      "result_method": null,
      "result_round": null,
      "event_page_link": "https://boxrec.com/en/event/902308",
      "bout_page_link": "https://boxrec.com/en/event/902308/3222973",
      "scorecards_page_link": null,
      "title_fight": null,
      "bout_rating": 3
    },
    {
      "bout_date": "May 24",
      "opponent_name": "Sean Hemphill",
      "opponent_id": "860317",
      "opponent_url": "https://boxrec.com/en/box-pro/860317",
      "opponent_weight": null,
      "opponent_record": "16-1-0",
      "recent_form": "WWWLWW",
      "venue_name": "T-Mobile Arena, Las Vegas",
      "referee_name": null,
      "judge_1_name": null,
      "judge_1_score": null,
      "judge_2_name": null,
      "judge_2_score": null,
      "judge_3_name": null,
      "judge_3_score": null,
      "num_rounds_scheduled": null,
      "result": "win",
      "result_method": null,
      "result_round": null,
      "event_page_link": "https://boxrec.com/en/event/892535",
      "bout_page_link": "https://boxrec.com/en/event/892535/3147245",
      "scorecards_page_link": null,
      "title_fight": null,
      "bout_rating": 2
    },
    {
      "bout_date": "Oct 23",
      "opponent_name": "Cristian Fabian Rios",
      "opponent_id": "445347",
      "opponent_url": "https://boxrec.com/en/box-pro/445347",
      "opponent_weight": null,
      "opponent_record": "23-18-3",
      "recent_form": "WLLLLL",
      "venue_name": "Stadthalle, Falkensee",
      "referee_name": null,
      "judge_1_name": null,
      "judge_1_score": null,
      "judge_2_name": null,
      "judge_2_score": null,
      "judge_3_name": null,
      "judge_3_score": null,
      "num_rounds_scheduled": null,
      "result": "win",
      "result_method": null,
      "result_round": null,
      "event_page_link": "https://boxrec.com/en/event/876163",
      "bout_page_link": "https://boxrec.com/en/event/876163/3051974",
      "scorecards_page_link": null,
      "title_fight": null,
      "bout_rating": 0
    },
    {
      "bout_date": "Nov 22",
      "opponent_name": "Abel Nicolas Adriel",
      "opponent_id": "524701",
      "opponent_url": "https://boxrec.com/en/box-pro/524701",
      "opponent_weight": null,
      "opponent_record": "26-25-3",
      "recent_form": "WWLLWL",
      "venue_name": "AGON Sportpark, Charlottenburg",
      "referee_name": null,
      "judge_1_name": null,
      "judge_1_score": null,
      "judge_2_name": null,
      "judge_2_score": null,
      "judge_3_name": null,
      "judge_3_score": null,
      "num_rounds_scheduled": null,
      "result": "win",
      "result_method": null,
      "result_round": null,
      "event_page_link": "https://boxrec.com/en/event/863653",
      "bout_page_link": "https://boxrec.com/en/event/863653/2911417",
      "scorecards_page_link": null,
      "title_fight": null,
      "bout_rating": 0
    },
    {
      "bout_date": "Jul 22",
      "opponent_name": "Evgeny Shvedenko",
      "opponent_id": "737983",
      "opponent_url": "https://boxrec.com/en/box-pro/737983",
      "opponent_weight": null,
      "opponent_record": "15-0-0",
      "recent_form": "WWWWWW",
      "venue_name": "Stadtwerke Arena, Erding",
      "referee_name": null,
      "judge_1_name": null,
      "judge_1_score": null,
      "judge_2_name": null,
      "judge_2_score": null,
      "judge_3_name": null,
      "judge_3_score": null,
      "num_rounds_scheduled": null,
      "result": "win",
      "result_method": null,
      "result_round": null,
      "event_page_link": "https://boxrec.com/en/event/856997",
      "bout_page_link": "https://boxrec.com/en/event/856997/2855278",
      "scorecards_page_link": null,
      "title_fight": null,
      "bout_rating": 2
    },
    {
      "bout_date": "Nov 21",
      "opponent_name": "Deneb Diaz",
      "opponent_id": "824428",
      "opponent_url": "https://boxrec.com/en/box-pro/824428",
      "opponent_weight": null,
      "opponent_record": "16-1-0",
      "recent_form": "WWLWW",
      "venue_name": "AGON Sportpark, Charlottenburg",
      "referee_name": null,
      "judge_1_name": null,
      "judge_1_score": null,
      "judge_2_name": null,
      "judge_2_score": null,
      "judge_3_name": null,
      "judge_3_score": null,
      "num_rounds_scheduled": null,
      "result": "win",
      "result_method": null,
      "result_round": null,
      "event_page_link": "https://boxrec.com/en/event/841667",
      "bout_page_link": "https://boxrec.com/en/event/841667/2740658",
      "scorecards_page_link": null,
      "title_fight": null,
      "bout_rating": 1
    },
    {
      "bout_date": "May 21",
      "opponent_name": "Dragan Lepei",
      "opponent_id": "669872",
      "opponent_url": "https://boxrec.com/en/box-pro/669872",
      "opponent_weight": null,
      "opponent_record": "19-3-2",
      "recent_form": "WLWWWL",
      "venue_name": "AGON Sportpark, Charlottenburg",
      "referee_name": null,
      "judge_1_name": null,
      "judge_1_score": null,
      "judge_2_name": null,
      "judge_2_score": null,
      "judge_3_name": null,
      "judge_3_score": null,
      "num_rounds_scheduled": null,
      "result": "win",
      "result_method": null,
      "result_round": null,
      "event_page_link": "https://boxrec.com/en/event/830061",
      "bout_page_link": "https://boxrec.com/en/event/830061/2652510",
      "scorecards_page_link": null,
      "title_fight": null,
      "bout_rating": 1
    },
    {
      "bout_date": "Feb 21",
      "opponent_name": "Gino Kanters",
      "opponent_id": "732941",
      "opponent_url": "https://boxrec.com/en/box-pro/732941",
      "opponent_weight": null,
      "opponent_record": "8-3-2",
      "recent_form": "DWWLWD",
      "venue_name": "AGON Sportpark, Charlottenburg",
      "referee_name": null,
      "judge_1_name": null,
      "judge_1_score": null,
      "judge_2_name": null,
      "judge_2_score": null,
      "judge_3_name": null,
      "judge_3_score": null,
      "num_rounds_scheduled": null,
      "result": "win",
      "result_method": null,
      "result_round": null,
      "event_page_link": "https://boxrec.com/en/event/827012",
      "bout_page_link": "https://boxrec.com/en/event/827012/2629861",
      "scorecards_page_link": null,
      "title_fight": null,
      "bout_rating": 1
    },
    {
      "bout_date": "Aug 20",
      "opponent_name": "Mathias Eklund",
      "opponent_id": "711500",
      "opponent_url": "https://boxrec.com/en/box-pro/711500",
      "opponent_weight": null,
      "opponent_record": "12-3-2",
      "recent_form": "LDLWLW",
      "venue_name": "Havelstudios, Charlottenburg",
      "referee_name": null,
      "judge_1_name": null,
      "judge_1_score": null,
      "judge_2_name": null,
      "judge_2_score": null,
      "judge_3_name": null,
      "judge_3_score": null,
      "num_rounds_scheduled": null,
      "result": "win",
      "result_method": null,
      "result_round": null,
      "event_page_link": "https://boxrec.com/en/event/811049",
      "bout_page_link": "https://boxrec.com/en/event/811049/2506207",
      "scorecards_page_link": null,
      "title_fight": null,
      "bout_rating": 0
    },
    {
      "bout_date": "Sep 19",
      "opponent_name": "Siarhei Khamitski",
      "opponent_id": "214262",
      "opponent_url": "https://boxrec.com/en/box-pro/214262",
      "opponent_weight": null,
      "opponent_record": "32-18-3",
      "recent_form": "LLLWLL",
      "venue_name": "Sporthalle, Zinnowitz",
      "referee_name": null,
      "judge_1_name": null,
      "judge_1_score": null,
      "judge_2_name": null,
      "judge_2_score": null,
      "judge_3_name": null,
      "judge_3_score": null,
      "num_rounds_scheduled": null,
      "result": "win",
      "result_method": null,
      "result_round": null,
      "event_page_link": "https://boxrec.com/en/event/795596",
      "bout_page_link": "https://boxrec.com/en/event/795596/2398422",
      "scorecards_page_link": null,
      "title_fight": null,
      "bout_rating": 1
    },
    {
      "bout_date": "Jul 19",
      "opponent_name": "Sebastian Horacio Papeschi",
      "opponent_id": "707760",
      "opponent_url": "https://boxrec.com/en/box-pro/707760",
      "opponent_weight": null,
      "opponent_record": "14-1-0",
      "recent_form": "WWWLWW",
      "venue_name": "Complejo Deportivo Teniente Origone, Justiniano Posse",
      "referee_name": null,
      "judge_1_name": null,
      "judge_1_score": null,
      "judge_2_name": null,
      "judge_2_score": null,
      "judge_3_name": null,
      "judge_3_score": null,
      "num_rounds_scheduled": null,
      "result": "win",
      "result_method": null,
      "result_round": null,
      "event_page_link": "https://boxrec.com/en/event/791450",
      "bout_page_link": "https://boxrec.com/en/event/791450/2370266",
      "scorecards_page_link": null,
      "title_fight": null,
      "bout_rating": 2
    },
    {
      "bout_date": "Jun 19",
      "opponent_name": "Roman Shkarupa",
      "opponent_id": "228205",
      "opponent_url": "https://boxrec.com/en/box-pro/228205",
      "opponent_weight": null,
      "opponent_record": "28-9-2",
      "recent_form": "LLLWLL",
      "venue_name": "Sport and Congress Center, Schwerin",
      "referee_name": null,
      "judge_1_name": null,
      "judge_1_score": null,
      "judge_2_name": null,
      "judge_2_score": null,
      "judge_3_name": null,
      "judge_3_score": null,
      "num_rounds_scheduled": null,
      "result": "win",
      "result_method": null,
      "result_round": null,
      "event_page_link": "https://boxrec.com/en/event/788879",
      "bout_page_link": "https://boxrec.com/en/event/788879/2356195",
      "scorecards_page_link": null,
      "title_fight": null,
      "bout_rating": 1
    },
    {
      "bout_date": "Mar 19",
      "opponent_name": "Basilio Silva",
      "opponent_id": "572663",
      "opponent_url": "https://boxrec.com/en/box-pro/572663",
      "opponent_weight": null,
      "opponent_record": "24-16-0",
      "recent_form": "WWWLLL",
      "venue_name": "Club Atletico Racing, Trelew",
      "referee_name": null,
      "judge_1_name": null,
      "judge_1_score": null,
      "judge_2_name": null,
      "judge_2_score": null,
      "judge_3_name": null,
      "judge_3_score": null,
      "num_rounds_scheduled": null,
      "result": "win",
      "result_method": null,
      "result_round": null,
      "event_page_link": "https://boxrec.com/en/event/784989",
      "bout_page_link": "https://boxrec.com/en/event/784989/2335805",
      "scorecards_page_link": null,
      "title_fight": null,
      "bout_rating": 0
    },
    {
      "bout_date": "Nov 18",
      "opponent_name": "Ivan Sakic",
      "opponent_id": "654184",
      "opponent_url": "https://boxrec.com/en/box-pro/654184",
      "opponent_weight": null,
      "opponent_record": "1-27-0",
      "recent_form": "LLLLLL",
      "venue_name": "Sporthalle Zur Kuhdrift 1, Neustadt Glewe",
      "referee_name": null,
      "judge_1_name": null,
      "judge_1_score": null,
      "judge_2_name": null,
      "judge_2_score": null,
      "judge_3_name": null,
      "judge_3_score": null,
      "num_rounds_scheduled": null,
      "result": "win",
      "result_method": null,
      "result_round": null,
      "event_page_link": "https://boxrec.com/en/event/776689",
      "bout_page_link": "https://boxrec.com/en/event/776689/2294312",
      "scorecards_page_link": null,
      "title_fight": null,
      "bout_rating": 0
    },
    {
      "bout_date": "Aug 18",
      "opponent_name": "Jose Luis Yana",
      "opponent_id": "790203",
      "opponent_url": "https://boxrec.com/en/box-pro/790203",
      "opponent_weight": null,
      "opponent_record": "7-2-0",
      "recent_form": "WWWWLL",
      "venue_name": "Gimnasio H\u00e9roes de Malvinas, Playa Union",
      "referee_name": null,
      "judge_1_name": null,
      "judge_1_score": null,
      "judge_2_name": null,
      "judge_2_score": null,
      "judge_3_name": null,
      "judge_3_score": null,
      "num_rounds_scheduled": null,
      "result": "win",
      "result_method": null,
      "result_round": null,
      "event_page_link": "https://boxrec.com/en/event/774364",
      "bout_page_link": "https://boxrec.com/en/event/774364/2275065",
      "scorecards_page_link": null,
      "title_fight": null,
      "bout_rating": 0
    },
    {
      "bout_date": "May 18",
      "opponent_name": "Martin Fidel Rios",
      "opponent_id": "636738",
      "opponent_url": "https://boxrec.com/en/box-pro/636738",
      "opponent_weight": null,
      "opponent_record": "22-16-4",
      "recent_form": "WLLLLL",
      "venue_name": "Club Deportivo Huracan, Trelew",
      "referee_name": null,
      "judge_1_name": null,
      "judge_1_score": null,
      "judge_2_name": null,
      "judge_2_score": null,
      "judge_3_name": null,
      "judge_3_score": null,
      "num_rounds_scheduled": null,
      "result": "win",
      "result_method": null,
      "result_round": null,
      "event_page_link": "https://boxrec.com/en/event/769977",
      "bout_page_link": "https://boxrec.com/en/event/769977/2251520",
      "scorecards_page_link": null,
      "title_fight": null,
      "bout_rating": 1
    },
    {
      "bout_date": "Feb 18",
      "opponent_name": "Miguel Eduardo Gorosito",
      "opponent_id": "653535",
      "opponent_url": "https://boxrec.com/en/box-pro/653535",
      "opponent_weight": null,
      "opponent_record": "4-3-0",
      "recent_form": "WWWLLW",
      "venue_name": "Nuevo Palacio Aurinegro, Puerto Madryn",
      "referee_name": null,
      "judge_1_name": null,
      "judge_1_score": null,
      "judge_2_name": null,
      "judge_2_score": null,
      "judge_3_name": null,
      "judge_3_score": null,
      "num_rounds_scheduled": null,
      "result": "win",
      "result_method": null,
      "result_round": null,
      "event_page_link": "https://boxrec.com/en/event/763755",
      "bout_page_link": "https://boxrec.com/en/event/763755/2223502",
      "scorecards_page_link": null,
      "title_fight": null,
      "bout_rating": 0
    },
    {
      "bout_date": "Dec 17",
      "opponent_name": "Cristian Fabian Rios",
      "opponent_id": "445347",
      "opponent_url": "https://boxrec.com/en/box-pro/445347",
      "opponent_weight": null,
      "opponent_record": "21-9-3",
      "recent_form": "WDLWLL",
      "venue_name": "Gimnasio Municipal N\u00ba 1, Trelew",
      "referee_name": null,
      "judge_1_name": null,
      "judge_1_score": null,
      "judge_2_name": null,
      "judge_2_score": null,
      "judge_3_name": null,
      "judge_3_score": null,
      "num_rounds_scheduled": null,
      "result": "win",
      "result_method": null,
      "result_round": null,
      "event_page_link": "https://boxrec.com/en/event/762009",
      "bout_page_link": "https://boxrec.com/en/event/762009/2212963",
      "scorecards_page_link": null,
      "title_fight": null,
      "bout_rating": 1
    },
    {
      "bout_date": "Jul 17",
      "opponent_name": "Emiliano German Vivas",
      "opponent_id": "740932",
      "opponent_url": "https://boxrec.com/en/box-pro/740932",
      "opponent_weight": null,
      "opponent_record": "3-6-0",
      "recent_form": "LWLLWL",
      "venue_name": "Parque La Pedrera, Villa Mercedes",
      "referee_name": null,
      "judge_1_name": null,
      "judge_1_score": null,
      "judge_2_name": null,
      "judge_2_score": null,
      "judge_3_name": null,
      "judge_3_score": null,
      "num_rounds_scheduled": null,
      "result": "win",
      "result_method": null,
      "result_round": null,
      "event_page_link": "https://boxrec.com/en/event/752671",
      "bout_page_link": "https://boxrec.com/en/event/752671/2172797",
      "scorecards_page_link": null,
      "title_fight": null,
      "bout_rating": 0
    },
    {
      "bout_date": "Apr 17",
      "opponent_name": "Carlos Dante Moyano",
      "opponent_id": "738667",
      "opponent_url": "https://boxrec.com/en/box-pro/738667",
      "opponent_weight": null,
      "opponent_record": "4-5-0",
      "recent_form": "LWWLWL",
      "venue_name": "Club Social y Deportivo San Vicente, Bell Ville",
      "referee_name": null,
      "judge_1_name": null,
      "judge_1_score": null,
      "judge_2_name": null,
      "judge_2_score": null,
      "judge_3_name": null,
      "judge_3_score": null,
      "num_rounds_scheduled": null,
      "result": "win",
      "result_method": null,
      "result_round": null,
      "event_page_link": "https://boxrec.com/en/event/749159",
      "bout_page_link": "https://boxrec.com/en/event/749159/2153676",
      "scorecards_page_link": null,
      "title_fight": null,
      "bout_rating": 0
    },
    {
      "bout_date": "Feb 17",
      "opponent_name": "Gustavo Rene Benitez",
      "opponent_id": "731449",
      "opponent_url": "https://boxrec.com/en/box-pro/731449",
      "opponent_weight": null,
      "opponent_record": "0-3-0",
      "recent_form": "LLL",
      "venue_name": "Club Ciclista Juninense, Jun\u00edn",
      "referee_name": null,
      "judge_1_name": null,
      "judge_1_score": null,
      "judge_2_name": null,
      "judge_2_score": null,
      "judge_3_name": null,
      "judge_3_score": null,
      "num_rounds_scheduled": null,
      "result": "win",
      "result_method": null,
      "result_round": null,
      "event_page_link": "https://boxrec.com/en/event/746775",
      "bout_page_link": "https://boxrec.com/en/event/746775/2141722",
      "scorecards_page_link": null,
      "title_fight": null,
      "bout_rating": 0
    },
    {
      "bout_date": "Jan 17",
      "opponent_name": "Victor Hugo Exner",
      "opponent_id": "773826",
      "opponent_url": "https://boxrec.com/en/box-pro/773826",
      "opponent_weight": null,
      "opponent_record": "2-1-0",
      "recent_form": "LWW",
      "venue_name": "Club Social y Deportivo Los Millonarios, Bragado",
      "referee_name": null,
      "judge_1_name": null,
      "judge_1_score": null,
      "judge_2_name": null,
      "judge_2_score": null,
      "judge_3_name": null,
      "judge_3_score": null,
      "num_rounds_scheduled": null,
      "result": "win",
      "result_method": null,
      "result_round": null,
      "event_page_link": "https://boxrec.com/en/event/745800",
      "bout_page_link": "https://boxrec.com/en/event/745800/2136999",
      "scorecards_page_link": null,
      "title_fight": null,
      "bout_rating": 1
    },
    {
      "bout_date": "Nov 16",
      "opponent_name": "Gaston Dario Avalos",
      "opponent_id": "736961",
      "opponent_url": "https://boxrec.com/en/box-pro/736961",
      "opponent_weight": null,
      "opponent_record": "2-3-0",
      "recent_form": "LLWWL",
      "venue_name": "Polideportivo Fortunato Perazzoli, San Carlos",
      "referee_name": null,
      "judge_1_name": null,
      "judge_1_score": null,
      "judge_2_name": null,
      "judge_2_score": null,
      "judge_3_name": null,
      "judge_3_score": null,
      "num_rounds_scheduled": null,
      "result": "win",
      "result_method": null,
      "result_round": null,
      "event_page_link": "https://boxrec.com/en/event/740760",
      "bout_page_link": "https://boxrec.com/en/event/740760/2120362",
      "scorecards_page_link": null,
      "title_fight": null,
      "bout_rating": 0
    }
  ],
  "created_at": "2025-07-31T04:18:52.117467+00:00",
  "updated_at": "2025-07-31T04:18:52.117478+00:00",
  "career": "2016-2025"
}