{
  "boxrec_id": "488530",
  "boxrec_url": "https://boxrec.com/en/box-pro/488530",
  "name": "Amanda Serrano",
  "slug": "amanda-serrano",
  "birth_name": null,
  "alias": "The Real Deal",
  "birth_date": null,
  "birth_place": "Puerto Rico",
  "nationality": "Puerto Rico",
  "stance": "southpaw",
  "height": "5\u2032 5\u00bd\u2033 / 166cm",
  "reach": "65\u00bd\u2033 / 166cm",
  "record": {
    "wins": 47,
    "losses": 4,
    "draws": 1,
    "kos": 0,
    "total_fights": 52
  },
  "division": "super light",
  "rating": "",
  "ranking": null,
  "titles": [
    "IBO World Feather",
    "WBO World Feather"
  ],
  "bouts_count": 52,
  "rounds_count": 256,
  "ko_percentage": "65.96%",
  "residence": "Carolina, Puerto Rico",
  "status": null,
  "career": "2009-2025",
  "debut": "2009-03-20",
  "sex": "female",
  "age": null,
  "company": null,
  "promoter": null,
  "manager_agent": null,
  "wiki": "https://boxrec.com/wiki/index.php?title=Human:488530",
  "bouts": [
    {
      "date": "2025-07-11",
      "opponent": "Katie Taylor",
      "opponent_id": "778185",
      "opponent_url": "https://boxrec.com/en/box-pro/778185",
      "opponent_record": "24-1-0",
      "recent_form": "WWWLWW",
      "result": "L",
      "method": null,
      "rounds": null,
      "venue": "Madison Square Garden, New York",
      "bout_rating": 5
    },
    {
      "date": "Nov 24",
      "opponent": "Katie Taylor",
      "opponent_id": "778185",
      "opponent_url": "https://boxrec.com/en/box-pro/778185",
      "opponent_record": "23-1-0",
      "recent_form": "WWWWLW",
      "result": "L",
      "method": null,
      "rounds": null,
      "venue": "AT&T Stadium, Arlington",
      "bout_rating": 5
    },
    {
      "date": "Jul 24",
      "opponent": "Stevie Morgan",
      "opponent_id": "873187",
      "opponent_url": "https://boxrec.com/en/box-pro/873187",
      "opponent_record": "14-1-0",
      "recent_form": "WWWWWW",
      "result": "W",
      "method": null,
      "rounds": null,
      "venue": "Amalie Arena, Tampa",
      "bout_rating": 2
    },
    {
      "date": "Oct 23",
      "opponent": "Danila Ramos",
      "opponent_id": "785703",
      "opponent_url": "https://boxrec.com/en/box-pro/785703",
      "opponent_record": "12-2-0",
      "recent_form": "WLWWWW",
      "result": "W",
      "method": null,
      "rounds": null,
      "venue": "Caribe Royale Orlando, Orlando",
      "bout_rating": 2
    },
    {
      "date": "Aug 23",
      "opponent": "Heather Hardy",
      "opponent_id": "618866",
      "opponent_url": "https://boxrec.com/en/box-pro/618866",
      "opponent_record": "24-2-0",
      "recent_form": "WWLLWW",
      "result": "W",
      "method": null,
      "rounds": null,
      "venue": "American Airlines Center, Dallas",
      "bout_rating": 2
    },
    {
      "date": "Feb 23",
      "opponent": "Erika Cruz Hernandez",
      "opponent_id": "751464",
      "opponent_url": "https://boxrec.com/en/box-pro/751464",
      "opponent_record": "15-1-0",
      "recent_form": "WWWWWW",
      "result": "W",
      "method": null,
      "rounds": null,
      "venue": "Madison Square Garden Theater, New York",
      "bout_rating": 3
    },
    {
      "date": "Sep 22",
      "opponent": "Sarah Mahfoud",
      "opponent_id": "786389",
      "opponent_url": "https://boxrec.com/en/box-pro/786389",
      "opponent_record": "11-0-0",
      "recent_form": "WWWWWW",
      "result": "W",
      "method": null,
      "rounds": null,
      "venue": "Manchester Arena, Manchester",
      "bout_rating": 3
    },
    {
      "date": "Apr 22",
      "opponent": "Katie Taylor",
      "opponent_id": "778185",
      "opponent_url": "https://boxrec.com/en/box-pro/778185",
      "opponent_record": "20-0-0",
      "recent_form": "WWWWWW",
      "result": "L",
      "method": null,
      "rounds": null,
      "venue": "Madison Square Garden, New York",
      "bout_rating": 5
    },
    {
      "date": "Dec 21",
      "opponent": "Miriam Gutierrez",
      "opponent_id": "793604",
      "opponent_url": "https://boxrec.com/en/box-pro/793604",
      "opponent_record": "14-1-0",
      "recent_form": "WWWWLW",
      "result": "W",
      "method": null,
      "rounds": null,
      "venue": "Amalie Arena, Tampa",
      "bout_rating": 1
    },
    {
      "date": "Aug 21",
      "opponent": "Yamileth Mercado",
      "opponent_id": "695318",
      "opponent_url": "https://boxrec.com/en/box-pro/695318",
      "opponent_record": "18-2-0",
      "recent_form": "WWWWWW",
      "result": "W",
      "method": null,
      "rounds": null,
      "venue": "Rocket Mortgage FieldHouse, Cleveland",
      "bout_rating": 3
    },
    {
      "date": "Mar 21",
      "opponent": "Daniela Romina Bermudez",
      "opponent_id": "531832",
      "opponent_url": "https://boxrec.com/en/box-pro/531832",
      "opponent_record": "29-3-3",
      "recent_form": "WWWWWW",
      "result": "W",
      "method": null,
      "rounds": null,
      "venue": "Plaza del Quinto Centenario, San Juan",
      "bout_rating": 3
    },
    {
      "date": "Dec 20",
      "opponent": "Dahianna Santana",
      "opponent_id": "115130",
      "opponent_url": "https://boxrec.com/en/box-pro/115130",
      "opponent_record": "36-12-0",
      "recent_form": "LLWLLL",
      "result": "W",
      "method": null,
      "rounds": null,
      "venue": "Hotel Catalonia Malecon Center, Santo Domingo",
      "bout_rating": 1
    },
    {
      "date": "Jan 20",
      "opponent": "Simone Aparecida da Silva",
      "opponent_id": "341705",
      "opponent_url": "https://boxrec.com/en/box-pro/341705",
      "opponent_record": "17-14-0",
      "recent_form": "LLWLWL",
      "result": "W",
      "method": null,
      "rounds": null,
      "venue": "Meridian at Island Gardens, Miami",
      "bout_rating": 0
    },
    {
      "date": "Sep 19",
      "opponent": "Heather Hardy",
      "opponent_id": "618866",
      "opponent_url": "https://boxrec.com/en/box-pro/618866",
      "opponent_record": "22-0-0",
      "recent_form": "WWWWWW",
      "result": "W",
      "method": null,
      "rounds": null,
      "venue": "Madison Square Garden Theater, New York",
      "bout_rating": 2
    },
    {
      "date": "Jan 19",
      "opponent": "Eva Voraberger",
      "opponent_id": "476832",
      "opponent_url": "https://boxrec.com/en/box-pro/476832",
      "opponent_record": "24-5-0",
      "recent_form": "WLWWWW",
      "result": "W",
      "method": null,
      "rounds": null,
      "venue": "Madison Square Garden Theater, New York",
      "bout_rating": 1
    },
    {
      "date": "Sep 18",
      "opponent": "Yamila Reynoso",
      "opponent_id": "672439",
      "opponent_url": "https://boxrec.com/en/box-pro/672439",
      "opponent_record": "11-4-3",
      "recent_form": "LLWWLW",
      "result": "W",
      "method": null,
      "rounds": null,
      "venue": "Barclays Center, Brooklyn",
      "bout_rating": 1
    },
    {
      "date": "Nov 17",
      "opponent": "Marilyn Hernandez",
      "opponent_id": "20450",
      "opponent_url": "https://boxrec.com/en/box-pro/20450",
      "opponent_record": "26-10-0",
      "recent_form": "WLWWLW",
      "result": "W",
      "method": null,
      "rounds": null,
      "venue": "Barclays Center, Brooklyn",
      "bout_rating": 1
    },
    {
      "date": "Jul 17",
      "opponent": "Edina Kiss",
      "opponent_id": "736625",
      "opponent_url": "https://boxrec.com/en/box-pro/736625",
      "opponent_record": "13-4-0",
      "recent_form": "LWWLWL",
      "result": "W",
      "method": null,
      "rounds": null,
      "venue": "Sheraton Puerto Rico Hotel & Casino, San Juan",
      "bout_rating": 1
    },
    {
      "date": "Apr 17",
      "opponent": "Dahianna Santana",
      "opponent_id": "115130",
      "opponent_url": "https://boxrec.com/en/box-pro/115130",
      "opponent_record": "35-8-0",
      "recent_form": "WWWLWL",
      "result": "W",
      "method": null,
      "rounds": null,
      "venue": "Barclays Center, Brooklyn",
      "bout_rating": 1
    },
    {
      "date": "Jan 17",
      "opponent": "Yazmin Rivas",
      "opponent_id": "184188",
      "opponent_url": "https://boxrec.com/en/box-pro/184188",
      "opponent_record": "35-9-1",
      "recent_form": "WWWLDW",
      "result": "W",
      "method": null,
      "rounds": null,
      "venue": "Barclays Center, Brooklyn",
      "bout_rating": 3
    },
    {
      "date": "Oct 16",
      "opponent": "Alexandra Lazar",
      "opponent_id": "723693",
      "opponent_url": "https://boxrec.com/en/box-pro/723693",
      "opponent_record": "8-1-0",
      "recent_form": "WLWWWW",
      "result": "W",
      "method": null,
      "rounds": null,
      "venue": "Caribe Hilton Hotel, San Juan",
      "bout_rating": 0
    },
    {
      "date": "Jul 16",
      "opponent": "Calista Silgado",
      "opponent_id": "589727",
      "opponent_url": "https://boxrec.com/en/box-pro/589727",
      "opponent_record": "14-6-3",
      "recent_form": "WLDWWL",
      "result": "W",
      "method": null,
      "rounds": null,
      "venue": "Barclays Center, Brooklyn",
      "bout_rating": 1
    },
    {
      "date": "Apr 16",
      "opponent": "Edina Kiss",
      "opponent_id": "736625",
      "opponent_url": "https://boxrec.com/en/box-pro/736625",
      "opponent_record": "6-0-0",
      "recent_form": "WWWWWW",
      "result": "W",
      "method": null,
      "rounds": null,
      "venue": "Cancha Ruben Zayas Montanez, Trujillo Alto",
      "bout_rating": 1
    },
    {
      "date": "Feb 16",
      "opponent": "Olivia Gerula",
      "opponent_id": "18509",
      "opponent_url": "https://boxrec.com/en/box-pro/18509",
      "opponent_record": "17-15-2",
      "recent_form": "LWWWLW",
      "result": "W",
      "method": null,
      "rounds": null,
      "venue": "BB King Blues Club & Grill, New York",
      "bout_rating": 1
    },
    {
      "date": "Nov 15",
      "opponent": "Djemilla Gontaruk",
      "opponent_id": "606651",
      "opponent_url": "https://boxrec.com/en/box-pro/606651",
      "opponent_record": "9-2-0",
      "recent_form": "WLWLWW",
      "result": "W",
      "method": null,
      "rounds": null,
      "venue": "Aviator Sports Complex, Brooklyn",
      "bout_rating": 0
    },
    {
      "date": "Sep 15",
      "opponent": "Fatuma Zarika",
      "opponent_id": "227147",
      "opponent_url": "https://boxrec.com/en/box-pro/227147",
      "opponent_record": "24-11-2",
      "recent_form": "WLLDLL",
      "result": "W",
      "method": null,
      "rounds": null,
      "venue": "The Space at Westbury, Westbury",
      "bout_rating": 2
    },
    {
      "date": "May 15",
      "opponent": "Fatuma Zarika",
      "opponent_id": "227147",
      "opponent_url": "https://boxrec.com/en/box-pro/227147",
      "opponent_record": "24-10-2",
      "recent_form": "LWLLDL",
      "result": "W",
      "method": null,
      "rounds": null,
      "venue": "W.C. Handy Pavilion, Memphis",
      "bout_rating": 2
    },
    {
      "date": "Feb 15",
      "opponent": "Marisol Reyes",
      "opponent_id": "372654",
      "opponent_url": "https://boxrec.com/en/box-pro/372654",
      "opponent_record": "14-9-1",
      "recent_form": "LWWLWL",
      "result": "W",
      "method": null,
      "rounds": null,
      "venue": "Sosua Convention Center, Puerto Plata",
      "bout_rating": 0
    },
    {
      "date": "Nov 14",
      "opponent": "Carla Torres",
      "opponent_id": "549996",
      "opponent_url": "https://boxrec.com/en/box-pro/549996",
      "opponent_record": "4-2-0",
      "recent_form": "WLWWLW",
      "result": "W",
      "method": null,
      "rounds": null,
      "venue": "The Space at Westbury, Westbury",
      "bout_rating": 2
    },
    {
      "date": "Aug 14",
      "opponent": "Maria Elena Maderna",
      "opponent_id": "453479",
      "opponent_url": "https://boxrec.com/en/box-pro/453479",
      "opponent_record": "13-8-3",
      "recent_form": "WLWWWW",
      "result": "W",
      "method": null,
      "rounds": null,
      "venue": "Estadio F.A.B., Buenos Aires",
      "bout_rating": 1
    },
    {
      "date": "Sep 13",
      "opponent": "Diana Collado",
      "opponent_id": "115129",
      "opponent_url": "https://boxrec.com/en/box-pro/115129",
      "opponent_record": "12-18-0",
      "recent_form": "WWLLLL",
      "result": "W",
      "method": null,
      "rounds": null,
      "venue": "Gimnasio Boxing Factory, Santiago de los Caballeros",
      "bout_rating": 0
    },
    {
      "date": "Sep 13",
      "opponent": "Kerri Hill",
      "opponent_id": "327619",
      "opponent_url": "https://boxrec.com/en/box-pro/327619",
      "opponent_record": "4-25-2",
      "recent_form": "WLLLLD",
      "result": "W",
      "method": null,
      "rounds": null,
      "venue": "Resorts World Casino, Queens",
      "bout_rating": 0
    },
    {
      "date": "Jun 13",
      "opponent": "Dominga Olivo",
      "opponent_id": "355244",
      "opponent_url": "https://boxrec.com/en/box-pro/355244",
      "opponent_record": "8-7-1",
      "recent_form": "LWLWLL",
      "result": "W",
      "method": null,
      "rounds": null,
      "venue": "Resorts World Casino, Queens",
      "bout_rating": 1
    },
    {
      "date": "Feb 13",
      "opponent": "Wanda Pena Ozuna",
      "opponent_id": "115127",
      "opponent_url": "https://boxrec.com/en/box-pro/115127",
      "opponent_record": "8-4-0",
      "recent_form": "LWLWWW",
      "result": "W",
      "method": null,
      "rounds": null,
      "venue": "Gran Arena del Cibao, Santiago de los Caballeros",
      "bout_rating": 0
    },
    {
      "date": "Dec 12",
      "opponent": "Lina Tejada",
      "opponent_id": "597886",
      "opponent_url": "https://boxrec.com/en/box-pro/597886",
      "opponent_record": "1-1-0",
      "recent_form": "WL",
      "result": "W",
      "method": null,
      "rounds": null,
      "venue": "Sosua Bay Grand Casino, Puerto Plata",
      "bout_rating": 1
    },
    {
      "date": "Sep 12",
      "opponent": "Grecia Novas Mateo",
      "opponent_id": "275961",
      "opponent_url": "https://boxrec.com/en/box-pro/275961",
      "opponent_record": "9-16-4",
      "recent_form": "WWWLWL",
      "result": "W",
      "method": null,
      "rounds": null,
      "venue": "Club Pueblo Nuevo, Villa Duarte",
      "bout_rating": 0
    },
    {
      "date": "Apr 12",
      "opponent": "Frida Wallberg",
      "opponent_id": "237041",
      "opponent_url": "https://boxrec.com/en/box-pro/237041",
      "opponent_record": "10-0-0",
      "recent_form": "WWWWWW",
      "result": "L",
      "method": null,
      "rounds": null,
      "venue": "Cloetta Center, Linkoping",
      "bout_rating": 3
    },
    {
      "date": "Feb 12",
      "opponent": "Ela Nunez",
      "opponent_id": "381685",
      "opponent_url": "https://boxrec.com/en/box-pro/381685",
      "opponent_record": "11-12-2",
      "recent_form": "LLWDWL",
      "result": "W",
      "method": null,
      "rounds": null,
      "venue": "Cicero Stadium, Cicero",
      "bout_rating": 2
    },
    {
      "date": "Nov 11",
      "opponent": "Grecia Novas Mateo",
      "opponent_id": "275961",
      "opponent_url": "https://boxrec.com/en/box-pro/275961",
      "opponent_record": "8-14-4",
      "recent_form": "WWWWWW",
      "result": "W",
      "method": null,
      "rounds": null,
      "venue": "Hotel Jaragua, Santo Domingo",
      "bout_rating": 0
    },
    {
      "date": "Sep 11",
      "opponent": "Kimberly Connor-Hamby",
      "opponent_id": "269626",
      "opponent_url": "https://boxrec.com/en/box-pro/269626",
      "opponent_record": "9-1-2",
      "recent_form": "WDWWWW",
      "result": "W",
      "method": null,
      "rounds": null,
      "venue": "Aviator Sports Complex, Brooklyn",
      "bout_rating": 1
    },
    {
      "date": "Aug 11",
      "opponent": "Diana Collado",
      "opponent_id": "115129",
      "opponent_url": "https://boxrec.com/en/box-pro/115129",
      "opponent_record": "12-14-0",
      "recent_form": "WWWWWW",
      "result": "W",
      "method": null,
      "rounds": null,
      "venue": "Parque del Este, Santo Domingo",
      "bout_rating": 0
    },
    {
      "date": "Jun 11",
      "opponent": "Jennifer Scott",
      "opponent_id": "490748",
      "opponent_url": "https://boxrec.com/en/box-pro/490748",
      "opponent_record": "2-3-0",
      "recent_form": "WWLLL",
      "result": "W",
      "method": null,
      "rounds": null,
      "venue": "Roseland Ballroom, New York",
      "bout_rating": 1
    },
    {
      "date": "Apr 11",
      "opponent": "Ela Nunez",
      "opponent_id": "381685",
      "opponent_url": "https://boxrec.com/en/box-pro/381685",
      "opponent_record": "9-8-1",
      "recent_form": "WLDLLL",
      "result": "W",
      "method": null,
      "rounds": null,
      "venue": "Fairgrounds Event Center, Hamburg",
      "bout_rating": 2
    },
    {
      "date": "Jan 11",
      "opponent": "Ela Nunez",
      "opponent_id": "381685",
      "opponent_url": "https://boxrec.com/en/box-pro/381685",
      "opponent_record": "9-7-1",
      "recent_form": "LWLDLL",
      "result": "W",
      "method": null,
      "rounds": null,
      "venue": "Turning Stone Resort & Casino, Verona",
      "bout_rating": 2
    },
    {
      "date": "Sep 10",
      "opponent": "Jennifer Encarnacion",
      "opponent_id": "327530",
      "opponent_url": "https://boxrec.com/en/box-pro/327530",
      "opponent_record": "2-4-0",
      "recent_form": "LWLLLW",
      "result": "W",
      "method": null,
      "rounds": null,
      "venue": "Coliseo Carlos 'Teo' Cruz, Santo Domingo",
      "bout_rating": 0
    },
    {
      "date": "Jun 10",
      "opponent": "Nydia Feliciano",
      "opponent_id": "495723",
      "opponent_url": "https://boxrec.com/en/box-pro/495723",
      "opponent_record": "2-0-2",
      "recent_form": "DWWD",
      "result": "W",
      "method": null,
      "rounds": null,
      "venue": "Tropicana Hotel & Casino, Atlantic City",
      "bout_rating": 1
    },
    {
      "date": "Feb 10",
      "opponent": "Lucia Larcinese",
      "opponent_id": "453555",
      "opponent_url": "https://boxrec.com/en/box-pro/453555",
      "opponent_record": "4-4-0",
      "recent_form": "WLLWWW",
      "result": "W",
      "method": null,
      "rounds": null,
      "venue": "Turning Stone Resort & Casino, Verona",
      "bout_rating": 1
    },
    {
      "date": "Nov 09",
      "opponent": "Ela Nunez",
      "opponent_id": "381685",
      "opponent_url": "https://boxrec.com/en/box-pro/381685",
      "opponent_record": "9-5-0",
      "recent_form": "WWWLWL",
      "result": "D",
      "method": null,
      "rounds": null,
      "venue": "Trump Taj Mahal, Atlantic City",
      "bout_rating": 2
    },
    {
      "date": "Jul 09",
      "opponent": "Christina Ruiz",
      "opponent_id": "502401",
      "opponent_url": "https://boxrec.com/en/box-pro/502401",
      "opponent_record": "1-0-0",
      "recent_form": "W",
      "result": "W",
      "method": null,
      "rounds": null,
      "venue": "Resorts Hotel & Casino, Atlantic City",
      "bout_rating": 1
    },
    {
      "date": "Jun 09",
      "opponent": "Carolina Martinez de Moreta",
      "opponent_id": "263713",
      "opponent_url": "https://boxrec.com/en/box-pro/263713",
      "opponent_record": "3-8-2",
      "recent_form": "LLDLLL",
      "result": "W",
      "method": null,
      "rounds": null,
      "venue": "Coliseo Carlos 'Teo' Cruz, Santo Domingo",
      "bout_rating": 0
    },
    {
      "date": "May 09",
      "opponent": "Brittany Cruz",
      "opponent_id": "444996",
      "opponent_url": "https://boxrec.com/en/box-pro/444996",
      "opponent_record": "3-1-0",
      "recent_form": "WWLW",
      "result": "W",
      "method": null,
      "rounds": null,
      "venue": "DoubleTree Hotel, Orlando",
      "bout_rating": 1
    },
    {
      "date": "Mar 09",
      "opponent": "Jackie Trivilino",
      "opponent_id": "488529",
      "opponent_url": "https://boxrec.com/en/box-pro/488529",
      "opponent_record": null,
      "recent_form": null,
      "result": "W",
      "method": null,
      "rounds": null,
      "venue": "Washington Avenue Armory, Albany",
      "bout_rating": 1
    }
  ]
}