{
  "boxrec_id": "851173",
  "boxrec_url": "https://boxrec.com/en/box-pro/851173",
  "name": "Israil Madrimov",
  "slug": "israil-madrimov",
  "birth_name": null,
  "alias": "The Dream",
  "birth_date": null,
  "birth_place": "Khiva, Uzbekistan",
  "nationality": "Uzbekistan",
  "stance": "orthodox",
  "height": "5\u2032 8\u00bd\u2033 / 174cm",
  "reach": "68\u00bd\u2033 / 174cm",
  "record": {
    "wins": 10,
    "losses": 2,
    "draws": 1,
    "kos": 0,
    "total_fights": 13
  },
  "division": "super welter",
  "rating": "",
  "ranking": null,
  "titles": [],
  "bouts_count": 13,
  "rounds_count": 98,
  "ko_percentage": "70%",
  "residence": "Indio, California, USA",
  "status": null,
  "career": "2018-2025",
  "debut": "2018-11-24",
  "sex": "male",
  "age": null,
  "company": null,
  "promoter": null,
  "manager_agent": "Vadim Kornilov",
  "wiki": "https://boxrec.com/wiki/index.php?title=Human:851173",
  "bouts": [
    {
      "date": "Feb 25",
      "opponent": "Vergil Ortiz Jr",
      "opponent_id": "766727",
      "opponent_url": "https://boxrec.com/en/box-pro/766727",
      "opponent_record": "22-0-0",
      "recent_form": "WWWWWW",
      "result": "L",
      "method": null,
      "rounds": null,
      "venue": "The Venue Riyadh Season, Riyadh",
      "bout_rating": 5
    },
    {
      "date": "Aug 24",
      "opponent": "Terence Crawford",
      "opponent_id": "447121",
      "opponent_url": "https://boxrec.com/en/box-pro/447121",
      "opponent_record": "40-0-0",
      "recent_form": "WWWWWW",
      "result": "L",
      "method": null,
      "rounds": null,
      "venue": "BMO Stadium, Los Angeles",
      "bout_rating": 5
    },
    {
      "date": "Mar 24",
      "opponent": "Magomed Kurbanov",
      "opponent_id": "722209",
      "opponent_url": "https://boxrec.com/en/box-pro/722209",
      "opponent_record": "25-0-0",
      "recent_form": "WWWWWW",
      "result": "W",
      "method": null,
      "rounds": null,
      "venue": "Kingdom Arena, Riyadh",
      "bout_rating": 4
    },
    {
      "date": "Apr 23",
      "opponent": "Raphael Igbokwe",
      "opponent_id": "732449",
      "opponent_url": "https://boxrec.com/en/box-pro/732449",
      "opponent_record": "16-3-0",
      "recent_form": "LWWWWL",
      "result": "W",
      "method": null,
      "rounds": null,
      "venue": "Boeing Center at Tech Port, San Antonio",
      "bout_rating": 1
    },
    {
      "date": "Jul 22",
      "opponent": "Michel Soro",
      "opponent_id": "469744",
      "opponent_url": "https://boxrec.com/en/box-pro/469744",
      "opponent_record": "35-3-1",
      "recent_form": "WWWWWL",
      "result": "D",
      "method": null,
      "rounds": null,
      "venue": "O2 Arena, Greenwich",
      "bout_rating": 4
    },
    {
      "date": "Dec 21",
      "opponent": "Michel Soro",
      "opponent_id": "469744",
      "opponent_url": "https://boxrec.com/en/box-pro/469744",
      "opponent_record": "35-2-1",
      "recent_form": "LWWWWW",
      "result": "W",
      "method": null,
      "rounds": null,
      "venue": "Hotel Renaissance, Tashkent",
      "bout_rating": 4
    },
    {
      "date": "Apr 21",
      "opponent": "Emmany Kalombo",
      "opponent_id": "729611",
      "opponent_url": "https://boxrec.com/en/box-pro/729611",
      "opponent_record": "14-0-0",
      "recent_form": "WWWWWW",
      "result": "W",
      "method": null,
      "rounds": null,
      "venue": "Humo Arena, Tashkent",
      "bout_rating": 3
    },
    {
      "date": "Aug 20",
      "opponent": "Eric Walker",
      "opponent_id": "671585",
      "opponent_url": "https://boxrec.com/en/box-pro/671585",
      "opponent_record": "20-2-0",
      "recent_form": "WWLWWW",
      "result": "W",
      "method": null,
      "rounds": null,
      "venue": "Downtown Tulsa Streets, Tulsa",
      "bout_rating": 2
    },
    {
      "date": "Feb 20",
      "opponent": "Charlie Navarro",
      "opponent_id": "251420",
      "opponent_url": "https://boxrec.com/en/box-pro/251420",
      "opponent_record": "29-9-0",
      "recent_form": "LLWWWW",
      "result": "W",
      "method": null,
      "rounds": null,
      "venue": "The Ford Center at The Star, Frisco",
      "bout_rating": 2
    },
    {
      "date": "Oct 19",
      "opponent": "Alejandro Barrera",
      "opponent_id": "424646",
      "opponent_url": "https://boxrec.com/en/box-pro/424646",
      "opponent_record": "27-5-0",
      "recent_form": "WWLWLL",
      "result": "W",
      "method": null,
      "rounds": null,
      "venue": "Madison Square Garden, New York",
      "bout_rating": 1
    },
    {
      "date": "Jun 19",
      "opponent": "Norberto Gonzalez",
      "opponent_id": "389950",
      "opponent_url": "https://boxrec.com/en/box-pro/389950",
      "opponent_record": "24-12-0",
      "recent_form": "WLLLLW",
      "result": "W",
      "method": null,
      "rounds": null,
      "venue": "Madison Square Garden, New York",
      "bout_rating": 1
    },
    {
      "date": "Mar 19",
      "opponent": "Frank Rojas",
      "opponent_id": "633197",
      "opponent_url": "https://boxrec.com/en/box-pro/633197",
      "opponent_record": "24-2-0",
      "recent_form": "WWLWLW",
      "result": "W",
      "method": null,
      "rounds": null,
      "venue": "Turning Stone Resort & Casino, Verona",
      "bout_rating": 0
    },
    {
      "date": "Nov 18",
      "opponent": "Vladimir Hernandez",
      "opponent_id": "456117",
      "opponent_url": "https://boxrec.com/en/box-pro/456117",
      "opponent_record": "10-2-0",
      "recent_form": "WLLWWW",
      "result": "W",
      "method": null,
      "rounds": null,
      "venue": "Mark G. Etess Arena, Hard Rock Hotel & Casino, Atlantic City",
      "bout_rating": 2
    }
  ]
}